README.txt
setup.cfg
setup.py
mio/__init__.py
mio/reader/__init__.py
mio/reader/ltm/__init__.py
mio/reader/ltm/lexer.py
mio/reader/ltm/parser.py
mio/reader/ltm/runtime.py
mio/reader/ltm/utils.py
tm.reader.ltm.egg-info/PKG-INFO
tm.reader.ltm.egg-info/SOURCES.txt
tm.reader.ltm.egg-info/dependency_links.txt
tm.reader.ltm.egg-info/entry_points.txt
tm.reader.ltm.egg-info/namespace_packages.txt
tm.reader.ltm.egg-info/not-zip-safe
tm.reader.ltm.egg-info/requires.txt
tm.reader.ltm.egg-info/top_level.txt